librarykelompok2/__init__.py
librarykelompok2/mylibrary.py
librarykelompok_2-0.1.dist-info/LICENSE
librarykelompok_2-0.1.dist-info/METADATA
librarykelompok_2-0.1.dist-info/WHEEL
librarykelompok_2-0.1.dist-info/top_level.txt
librarykelompok_2-0.1.dist-info/RECORD
