Metadata-Version: 2.1
Name: librarykelompok-2
Version: 0.1
Summary: Kelompok 2
Home-page: https://github.com/hanifaslamm
Author: hanifaslamm
Author-email: aslamhanif141@gmail.com
License: MIT
Keywords: Hello
Platform: UNKNOWN
Classifier: Development Status :: 1 - Planning
License-File: LICENSE
